indico_storage_xrootd.py
indico_plugin_storage_xrootd-1.0.dist-info/DESCRIPTION.rst
indico_plugin_storage_xrootd-1.0.dist-info/METADATA
indico_plugin_storage_xrootd-1.0.dist-info/RECORD
indico_plugin_storage_xrootd-1.0.dist-info/WHEEL
indico_plugin_storage_xrootd-1.0.dist-info/entry_points.txt
indico_plugin_storage_xrootd-1.0.dist-info/metadata.json
indico_plugin_storage_xrootd-1.0.dist-info/top_level.txt
